CHANGES.rst
CONTRIBUTORS.rst
LICENSE
MANIFEST.in
Makefile
README.rst
setup.py
boom/__init__.py
boom/boom.py
boom/pgbar.py
boom/util.py
boom.egg-info/PKG-INFO
boom.egg-info/SOURCES.txt
boom.egg-info/dependency_links.txt
boom.egg-info/entry_points.txt
boom.egg-info/not-zip-safe
boom.egg-info/requires.txt
boom.egg-info/top_level.txt
boom/tests/__init__.py
boom/tests/test_boom.py
boom/tests/test_pgbar.py