Metadata-Version: 1.1
Name: boom
Version: 1.0
Summary: Simple HTTP Load tester
Home-page: https://github.com/tarekziade/boom
Author: Tarek Ziade
Author-email: tarek@ziade.org
License: UNKNOWN
Platform: UNKNOWN
Classifier: Programming Language :: Python
Classifier: License :: OSI Approved :: Apache Software License
Classifier: Development Status :: 1 - Planning
